Metadata-Version: 2.1
Name: directedit
Version: 1.0.2
Summary: Lightweight managing folder contents library
Author: Monsler
Author-email: galileoru22@gmail.com
Classifier: Programming Language :: Python :: 3
Classifier: License :: OSI Approved :: MIT License
Classifier: Operating System :: OS Independent
